bedpy/__init__.py
bedpy/bed6/__init__.py
bedpy/bed6/base.py
bedpy/bed6/bed6.py
bedpy/bed6file/__init__.py
bedpy/bed6file/bed6file.py
bedpy/data/hg38.chrom.sizes
bedpy/encoders/__init__.py
bedpy/encoders/fastacharacter.py
bedpy/encoders/fastasequence.py
bedpy/encoders/labelrangesindex.py
bedpy/encoders/labelrangessequence.py
bedpy/encoders/onehotcharacter.py
bedpy/encoders/onehotsequence.py
bedpy/encoders/probabilityclassindex.py
bedpy/encoders/probabilityclasssequence.py
bedpy/encoders/sequence.py
bedpy/pbed6/__init__.py
bedpy/pbed6/base.py
bedpy/pbed6/pbed6.py
bedpy/ranges/__init__.py
bedpy/ranges/classrange.py
bedpy/ranges/classranges.py
bedpy/seq10/__init__.py
bedpy/seq10/base.py
bedpy/seq10/seq10.py
bedpy/seq10/visualizations.py
bedpy/utils/__init__.py
bedpy/utils/constants.py
bedpy/utils/files.py
bedpy/utils/misc.py
bedpy-0.0.5.dist-info/LICENSE
bedpy-0.0.5.dist-info/METADATA
bedpy-0.0.5.dist-info/WHEEL
bedpy-0.0.5.dist-info/top_level.txt
bedpy-0.0.5.dist-info/RECORD
