Metadata-Version: 2.1
Name: bedpy
Version: 0.0.5
Summary: Making bed files computable
Home-page: https://gitlab.com/SumNeuron/bedpy/
Author: Sumner Magruder
Author-email: sumner.magruder@zmnh.uni-hamburg.de
License: UNKNOWN
Platform: UNKNOWN
Classifier: Programming Language :: Python :: 3.6
Classifier: License :: OSI Approved :: MIT License
Classifier: Operating System :: OS Independent
